Nivel03/counterMod10.v
module counterMod10 (
    input wire [3:0] CNT_in,
    input wire loadn, clrn, clk, en,
    output reg [3:0] CNT, 
    output reg tc, zero
);

always @(posedge clk) begin
        if(clrn == 0) CNT <= 0;
        else if(loadn == 0) CNT <= CNT_in; 
        else if (CNT == 0 && en == 1) CNT <= 9;
        else if (CNT > 9) CNT <= 9; 
        else if(en == 1) CNT <= CNT - 1;
        else CNT <= CNT;
end

always @(CNT or en) begin
    if((en == 1) && (CNT == 4'b0000)) begin
        tc <= 1; 
        zero <= 1;
    end
    else begin
        tc <= 0;
        zero <= 0;
    end
end

endmodule

Nivel03/counterMod10_tb.v
`timescale 1ns/1ps
`include "counterMod10.v"

module counterMod10_tb ();

reg [0:3] CNT_in_tb;
reg loadn_tb; reg clrn_tb; reg clk_tb; reg en_tb;
wire [0:3] CNT_tb;
wire tc_tb; wire zero_tb;

counterMod10 UUT(.CNT_in(CNT_in_tb), .loadn(loadn_tb), .clrn(clrn_tb), .clk(clk_tb), .en(en_tb), .CNT(CNT_tb), .tc(tc_tb), .zero(zero_tb));

always #5 clk_tb = ~clk_tb;

initial begin
    $dumpfile("counterMod10_tb.vcd");
    $dumpvars(0, counterMod10_tb);

    clk_tb = 0;
    clrn_tb = 1; en_tb = 0;
    loadn_tb = 0; CNT_in_tb = 4'b0111;
    
    #12
    loadn_tb = 1;
    #5
    en_tb = 1;
    #120
    CNT_in_tb = 4'b1010;
    loadn_tb = 0;
    #10
    loadn_tb = 1;
    #20
    en_tb = 0;
    #20
    $stop;
 
end
endmodule

Nivel03/counterMod10_tb.vcd
$date
	Wed Dec 15 15:32:08 2021
$end
$version
	Icarus Verilog
$end
$timescale
	1ps
$end
$scope module counterMod10_tb $end
$var wire 1 ! zero_tb $end
$var wire 1 " tc_tb $end
$var wire 4 # CNT_tb [0:3] $end
$var reg 4 $ CNT_in_tb [0:3] $end
$var reg 1 % clk_tb $end
$var reg 1 & clrn_tb $end
$var reg 1 ' en_tb $end
$var reg 1 ( loadn_tb $end
$scope module UUT $end
$var wire 4 ) CNT_in [3:0] $end
$var wire 1 % clk $end
$var wire 1 & clrn $end
$var wire 1 ' en $end
$var wire 1 ( loadn $end
$var reg 4 * CNT [3:0] $end
$var reg 1 " tc $end
$var reg 1 ! zero $end
$upscope $end
$upscope $end
$enddefinitions $end
#0
$dumpvars
bx *
b111 )
0(
0'
1&
0%
b111 $
bx #
0"
0!
$end
#5000
b111 #
b111 *
1%
#10000
0%
#12000
1(
#15000
1%
#17000
1'
#20000
0%
#25000
b110 #
b110 *
1%
#30000
0%
#35000
b101 #
b101 *
1%
#40000
0%
#45000
b100 #
b100 *
1%
#50000
0%
#55000
b11 #
b11 *
1%
#60000
0%
#65000
b10 #
b10 *
1%
#70000
0%
#75000
b1 #
b1 *
1%
#80000
0%
#85000
1!
1"
b0 #
b0 *
1%
#90000
0%
#95000
b1001 #
b1001 *
1%
#100000
0%
#105000
b1000 #
b1000 *
1%
#110000
0%
#115000
b111 #
b111 *
1%
#120000
0%
#125000
b110 #
b110 *
1%
#130000
0%
#135000
b101 #
b101 *
1%
#137000
0(
b1010 $
b1010 )
#140000
0%
#145000
b1010 #
b1010 *
1%
#147000
1(
#150000
0%
#155000
b1001 #
b1001 *
1%
#160000
0%
#165000
b1000 #
b1000 *
1%
#167000
0!
0"
0'
