Nivel03/counterMod6.v
module counterMod6 (
    input wire [3:0] CNT_in,
    input wire loadn, clrn, clk, en,
    output reg [3:0] CNT, 
    output reg tc, zero
);

always @(posedge clk) begin
        if(clrn == 0) CNT <= 0;
        else if(loadn == 0) CNT <= CNT_in; 
        else if (CNT == 0 && en == 1) CNT <= 5;
        else if (CNT > 5) CNT <= 5;
        else if(en == 1) CNT <= CNT - 1;
        else CNT <= CNT;

end
always @(CNT or en) begin
    if((en == 1) && (CNT == 4'b0000)) begin
        tc <= 1; 
        zero <= 1;
    end
    else begin
        tc <= 0;
        zero <= 0;
    end
end

endmodule

Nivel03/counterMod6_tb.v
`timescale 1ns/1ps
`include "counterMod6.v"

module counterMod6_tb ();

reg [0:3] CNT_in_tb;
reg loadn_tb; reg clrn_tb; reg clk_tb; reg en_tb;
wire [0:3] CNT_tb;
wire tc_tb; wire zero_tb;

counterMod6 UUT(.CNT_in(CNT_in_tb), .loadn(loadn_tb), .clrn(clrn_tb), .clk(clk_tb), .en(en_tb), .CNT(CNT_tb), .tc(tc_tb), .zero(zero_tb));

always #5 clk_tb = ~clk_tb;

initial begin
    $dumpfile("counterMod6_tb.vcd");
    $dumpvars(0, counterMod6_tb);

    clk_tb = 0;
    clrn_tb = 1; en_tb = 0;
    loadn_tb = 0; CNT_in_tb = 4'b0111;
    
    #12
    loadn_tb = 1;
    #5
    en_tb = 1;
    #40
    CNT_in_tb = 4'b1010;
    loadn_tb = 0;
    #10
    loadn_tb = 1;
    #20
    en_tb = 0;
    #20
    $stop;
 
end
endmodule

Nivel03/counterMod6_tb.vcd
$date
	Wed Dec 08 03:32:17 2021
$end
$version
	Icarus Verilog
$end
$timescale
	1ps
$end
$scope module counterMod6_tb $end
$var wire 1 ! zero_tb $end
$var wire 1 " tc_tb $end
$var wire 4 # CNT_tb [0:3] $end
$var reg 4 $ CNT_in_tb [0:3] $end
$var reg 1 % clk_tb $end
$var reg 1 & clrn_tb $end
$var reg 1 ' en_tb $end
$var reg 1 ( loadn_tb $end
$scope module UUT $end
$var wire 4 ) CNT_in [3:0] $end
$var wire 1 % clk $end
$var wire 1 & clrn $end
$var wire 1 ' en $end
$var wire 1 ( loadn $end
$var reg 4 * CNT [3:0] $end
$var reg 1 " tc $end
$var reg 1 ! zero $end
$upscope $end
$upscope $end
$enddefinitions $end
#0
$dumpvars
bx *
b111 )
0(
0'
1&
0%
b111 $
bx #
0"
0!
$end
#5000
b111 #
b111 *
1%
#10000
0%
#12000
1(
#15000
b101 #
b101 *
1%
#17000
1'
#20000
0%
#25000
b100 #
b100 *
1%
#30000
0%
#35000
b11 #
b11 *
1%
#40000
0%
#45000
b10 #
b10 *
1%
#50000
0%
#55000
b1 #
b1 *
1%
#57000
0(
b1010 $
b1010 )
#60000
0%
#65000
b1010 #
b1010 *
1%
#67000
1(
#70000
0%
#75000
b101 #
b101 *
1%
#80000
0%
#85000
b100 #
b100 *
1%
#87000
0'
