Nivel03/logica_controle.v
module logica_controle (
    input wire startn, stopn, clearn, door_closed, timer_done,
    output reg S, R
);

always @(*) begin
    if(clearn == 0) begin #1000 S <= 0; #1000 R <= 1; end //tempo de espera para o timer zerar
    if((stopn == 0) || (timer_done == 1) || (door_closed == 0)) begin
        S <= 0; R <= 1;
    end
    else if(startn == 0 && door_closed)begin
        S <= 1; R <= 0;
    end 
end
    
endmodule

Nivel03/logica_controle_tb.v
`timescale 1ns/1ps
`include "logica_controle.v"

module logica_controle_tb ();

reg startn_tb; reg stopn_tb; reg clearn_tb; reg door_closed_tb; reg timer_done_tb;
wire S_tb, R_tb;

logica_controle UUT(.startn(startn_tb), .stopn(stopn_tb), .door_closed(door_closed_tb), .timer_done(timer_done_tb),
.S(S_tb), .R(R_tb));

initial begin
    $dumpfile("logica_controle_tb.vcd");
    $dumpvars(0, logica_controle_tb);
    #10

    //PORTA FECHADA MAS NAO PRESSIONOU O BOTAO START
    startn_tb = 1; door_closed_tb = 1;
    #10
    //PRESSIONOU O BOTAO START E A PORTA FOI FECHADA ANTERIORMENTE
    startn_tb = 0;
    #10
    //SOLTOU O BOTAO START
    startn_tb = 1;
    #5
    //PRESSIONOU O BOTAO START
    startn_tb = 0;
    #5
    //ABRIU A PORTA
    door_closed_tb = 0; 
    #5
    //FECHOU A PORTA
    door_closed_tb = 1;
    #5
    //PRESSIONOU O BOTAO START
    startn_tb = 0;
    #5
    //PRESSIONOU O BOTAO STOP
    stopn_tb = 0;
    #5

    $finish;


end
    
endmodule

Nivel03/logica_controle_tb.vcd
$date
	Thu Dec 16 01:29:05 2021
$end
$version
	Icarus Verilog
$end
$timescale
	1ps
$end
$scope module logica_controle_tb $end
$var wire 1 ! S_tb $end
$var wire 1 " R_tb $end
$var reg 1 # door_closed_tb $end
$var reg 1 $ startn_tb $end
$var reg 1 % stopn_tb $end
$var reg 1 & timer_done_tb $end
$scope module UUT $end
$var wire 1 ' clearn $end
$var wire 1 # door_closed $end
$var wire 1 $ startn $end
$var wire 1 % stopn $end
$var wire 1 & timer_done $end
$var reg 1 " R $end
$var reg 1 ! S $end
$upscope $end
$upscope $end
$enddefinitions $end
#0
$dumpvars
z'
x&
x%
x$
x#
x"
x!
$end
#10000
1#
1$
#20000
0"
1!
0$
#30000
1$
#35000
0$
#40000
1"
0!
0#
#45000
0"
1!
1#
#55000
1"
0!
0%
