Nivel03/nonrecycle_counter.v
module nonrecycle_counter (
    input wire clr, clk,
    output reg out
);
reg[2:0] count;
    always @(posedge clk or clr) begin
        if(clr == 1) begin count <= 0; out <= 0; end
        else if (count == 7) count <= 7;
        else count <= count+1;
        if(count == 4) out <= 1;
    end
endmodule

Nivel03/nonrecycle_counter_tb.v
`timescale 1ms/1ns
`include "nonrecycle_counter.v"

module nonrecycle_counter_tb ();

reg clr_tb; reg clk_tb;
wire out_tb;

nonrecycle_counter UUT( .clr(clr_tb), .clk(clk_tb), .out(out_tb));

always #10 clk_tb = ~clk_tb;

initial begin
    $dumpfile("nonrecycle_counter_tb.vcd");
    $dumpvars(0, nonrecycle_counter_tb);
    
    clr_tb = 1;
    clk_tb = 0;

    #50
    clr_tb = 0;
    #200
    clr_tb = 1;
    #30

    $stop;
    /*
    loadn_tb = 0; CNT_in_tb = 4'b0011;
    
    #12
    loadn_tb = 1;
    en_tb = 1;
    #50
    CNT_in_tb = 4'b1010;
    loadn_tb = 0;
    #10
    loadn_tb = 1;
    #20
    en_tb = 0;
    #20
    $stop;*/
 
end
endmodule

Nivel03/nonrecycle_counter_tb.vcd
$date
	Sun Dec 12 22:16:36 2021
$end
$version
	Icarus Verilog
$end
$timescale
	1ns
$end
$scope module nonrecycle_counter_tb $end
$var wire 1 ! out_tb $end
$var reg 1 " clk_tb $end
$var reg 1 # clr_tb $end
$scope module UUT $end
$var wire 1 " clk $end
$var wire 1 # clr $end
$var reg 3 $ count [2:0] $end
$var reg 1 ! out $end
$upscope $end
$upscope $end
$enddefinitions $end
#0
$dumpvars
b0 $
1#
0"
0!
$end
#10000000
1"
#20000000
0"
#30000000
1"
#40000000
0"
#50000000
b1 $
1"
0#
#60000000
0"
#70000000
b10 $
1"
#80000000
0"
#90000000
b11 $
1"
#100000000
0"
#110000000
b100 $
1"
#120000000
0"
#130000000
1!
b101 $
1"
#140000000
0"
#150000000
b110 $
1"
#160000000
0"
#170000000
b111 $
1"
#180000000
0"
#190000000
1"
#200000000
0"
#210000000
1"
#220000000
0"
#230000000
1"
#240000000
0"
#250000000
0!
b0 $
1"
1#
