Nivel03/PriorityEncoder.v

module PriorityEncoder(
  input wire [9:0] keypad,
  input wire enablen,
  output reg [3:0] D,
  output reg V
);
  
  always @ (*)
  begin
	if(enablen) begin
		D = 0; V = 1;
	end else begin
		D = (keypad[9]) ? (9) :
			 (keypad[8]) ? (8) :
			 (keypad[7]) ? (7) :
			 (keypad[6]) ? (6) :
			 (keypad[5]) ? (5) :
			 (keypad[4]) ? (4) :
			 (keypad[3]) ? (3) :
			 (keypad[2]) ? (2) :
			 (keypad[1]) ? (1) :
			 (keypad[0]) ? (0) : 4'bxxxx;
		V = (keypad[9]) ? 0 :
			 (keypad[8]) ? 0 :
			 (keypad[7]) ? 0 :
			 (keypad[6]) ? 0 :
			 (keypad[5]) ? 0 :
			 (keypad[4]) ? 0 :
			 (keypad[3]) ? 0 :
			 (keypad[2]) ? 0 :
			 (keypad[1]) ? 0 :
			 (keypad[0]) ? 0 : 1;
   end
  end
  
  
endmodule

Nivel03/PriorityEncoder_tb.v
`timescale 1ms/1us
`include "PriorityEncoder.v"

module PriorityEncoder_tb();
	
	reg [9:0] inputs;
	reg enable_low;
	wire [3:0] outp;
	wire V_tb;
	
	integer en_control;
	integer control;
	
	PriorityEncoder DUT(
		.keypad(inputs),
		.enablen(enable_low),
		.D(outp),
		.V(V_tb)
	);
	
	initial
	begin
		$dumpfile("PriorityEncoder_tb.vcd");
        $dumpvars(0,PriorityEncoder_tb);
		inputs = 9'b000000000;

		enable_low = 0;
		inputs[9] = 1;
		#5
		inputs[9] = 0;
		#10
		inputs[8] = 1;
		#5
		inputs[8] = 0;
		#5
		inputs[0] = 1;
		#10
		inputs[0] = 0;
		#10
		inputs[5] = 1;
		#10
		inputs[5] = 0;
		#10
		$finish;

	end
	
endmodule

Nivel03/PriorityEncoder_tb.vcd
$date
	Sun Dec 12 23:58:46 2021
$end
$version
	Icarus Verilog
$end
$timescale
	1us
$end
$scope module PriorityEncoder_tb $end
$var wire 4 ! outp [3:0] $end
$var wire 1 " V_tb $end
$var reg 1 # enable_low $end
$var reg 10 $ inputs [9:0] $end
$scope module DUT $end
$var wire 1 # enablen $end
$var wire 10 % keypad [9:0] $end
$var reg 4 & D [3:0] $end
$var reg 1 " V $end
$upscope $end
$upscope $end
$enddefinitions $end
#0
$dumpvars
b1001 &
b1000000000 %
b1000000000 $
0#
1"
b1001 !
$end
#5000
0"
bx !
bx &
b0 $
b0 %
#15000
1"
b1000 !
b1000 &
b100000000 $
b100000000 %
#20000
0"
bx !
bx &
b0 $
b0 %
#25000
1"
b0 !
b0 &
b1 $
b1 %
#35000
0"
bx !
bx &
b0 $
b0 %
#45000
1"
b101 !
b101 &
b100000 $
b100000 %
#55000
0"
bx !
bx &
b0 $
b0 %
