Nivel03/SRlatch.v
module SRlatch (
    input wire S, R,
    output wire Q, Qn
);

wire Q_int, Qn_int;

assign Q_int = ~(R || Qn_int);
assign Qn_int = ~(S || Q_int);
assign Q = Q_int;
assign Qn = Qn_int;
    
endmodule

Nivel03/logica_controle.v
module logica_controle (
    input wire startn, stopn, clearn, door_closed, timer_done,
    output reg S, R
);

always @(*) begin
    if(clearn == 0) begin #1000 S <= 0; #1000 R <= 1; end //tempo de espera para o timer zerar
    if((stopn == 0) || (timer_done == 1) || (door_closed == 0)) begin
        S <= 0; R <= 1;
    end
    else if(startn == 0 && door_closed)begin
        S <= 1; R <= 0;
    end 
end
    
endmodule

Nivel02/controle_magnetron.v
`include "..\Nivel03\logica_controle.v"
`include "..\Nivel03\SRlatch.v"

module controle_magnetron (
    input wire startn, stopn, clearn, door_closed, timer_done,
    output wire mag_on
);
wire S, R, magn_on;

logica_controle controle(startn, stopn, clearn, door_closed, timer_done, S, R);
SRlatch latch(S, R, mag_on, magn_on);

    
endmodule

Nivel02/controle_magnetron_tb.v
`timescale 1ns/1ps
`include "controle_magnetron.v"

module controle_magnetron_tb ();

reg startn_tb; reg stopn_tb; reg clearn_tb; reg door_closed_tb; reg timer_done_tb;
wire mag_on_tb;

controle_magnetron UUT(.startn(startn_tb), .stopn(stopn_tb), .door_closed(door_closed_tb), .timer_done(timer_done_tb),
.mag_on(mag_on_tb));

initial begin
    $dumpfile("controle_magnetron_tb.vcd");
    $dumpvars(0, controle_magnetron_tb);
    #10

    //PORTA FECHADA MAS NAO PRESSIONOU O BOTAO START
    startn_tb = 1; door_closed_tb = 1;
    #10
    //PRESSIONOU O BOTAO START E A PORTA FOI FECHADA ANTERIORMENTE
    startn_tb = 0;
    #10
    //SOLTOU O BOTAO START
    startn_tb = 1;
    #5
    //PRESSIONOU O BOTAO START
    startn_tb = 0;
    #5
    //ABRIU A PORTA
    door_closed_tb = 0; 
    #5
    //FECHOU A PORTA
    door_closed_tb = 1;
    #5
    //PRESSIONOU O BOTAO START
    startn_tb = 0;
    #5
    //PRESSIONOU O BOTAO STOP
    stopn_tb = 0;
    #5
    //PRESSIONOU O BOTAO START
    stopn_tb = 1;
    startn_tb = 0;
    #5
    timer_done_tb = 1;
    #10

    $finish;


end
    
endmodule

Nivel02/controle_magnetron_tb.vcd
$date
	Thu Dec 16 01:30:18 2021
$end
$version
	Icarus Verilog
$end
$timescale
	1ps
$end
$scope module controle_magnetron_tb $end
$var wire 1 ! mag_on_tb $end
$var reg 1 " door_closed_tb $end
$var reg 1 # startn_tb $end
$var reg 1 $ stopn_tb $end
$var reg 1 % timer_done_tb $end
$scope module UUT $end
$var wire 1 & clearn $end
$var wire 1 " door_closed $end
$var wire 1 # startn $end
$var wire 1 $ stopn $end
$var wire 1 % timer_done $end
$var wire 1 ' magn_on $end
$var wire 1 ! mag_on $end
$var wire 1 ( S $end
$var wire 1 ) R $end
$scope module controle $end
$var wire 1 & clearn $end
$var wire 1 " door_closed $end
$var wire 1 # startn $end
$var wire 1 $ stopn $end
$var wire 1 % timer_done $end
$var reg 1 ) R $end
$var reg 1 ( S $end
$upscope $end
$scope module latch $end
$var wire 1 ! Q $end
$var wire 1 * Q_int $end
$var wire 1 ' Qn $end
$var wire 1 + Qn_int $end
$var wire 1 ) R $end
$var wire 1 ( S $end
$upscope $end
$upscope $end
$upscope $end
$enddefinitions $end
#0
$dumpvars
x+
x*
x)
x(
x'
z&
x%
x$
x#
x"
x!
$end
#10000
1"
1#
#20000
1!
1*
0'
0+
0)
1(
0#
#30000
1#
#35000
0#
#40000
1'
1+
0!
0*
1)
0(
0"
#45000
1!
1*
0'
0+
0)
1(
1"
#55000
1'
1+
0!
0*
1)
0(
0$
#60000
1!
1*
0'
0+
0)
1(
1$
#65000
1'
1+
0!
0*
1)
0(
1%
