Nivel02/decoder_7seg.v
module decoder_7seg(
     input wire [3:0] sec_ones, sec_tens, min,
     output reg [0:6] sec_ones_segs, sec_tens_segs, min_segs
    );

    always @(*) //ativo em nivel baixo
    begin
        case (sec_ones) 
           0 : sec_ones_segs = 7'b0000001;
            1 : sec_ones_segs = 7'b1001111;
            2 : sec_ones_segs = 7'b0010010;
            3 : sec_ones_segs = 7'b0000110;
            4 : sec_ones_segs = 7'b1001100;
            5 : sec_ones_segs = 7'b0100100;
            6 : sec_ones_segs = 7'b0100000;
            7 : sec_ones_segs = 7'b0001111;
            8 : sec_ones_segs = 7'b0000000;
            9 : sec_ones_segs = 7'b0000100;
            default : sec_ones_segs = 7'b1111111; 

        endcase
         case (sec_tens) 
            0 : sec_tens_segs = 7'b0000001;
            1 : sec_tens_segs = 7'b1001111;
            2 : sec_tens_segs = 7'b0010010;
            3 : sec_tens_segs = 7'b0000110;
            4 : sec_tens_segs = 7'b1001100;
            5 : sec_tens_segs = 7'b0100100;
            6 : sec_tens_segs = 7'b0100000;
            7 : sec_tens_segs = 7'b0001111;
            8 : sec_tens_segs = 7'b0000000;
            9 : sec_tens_segs = 7'b0000100;
            default : sec_tens_segs = 7'b1111111; 
        endcase
         case (min) 
            0 : min_segs = 7'b0000001;
            1 : min_segs = 7'b1001111;
            2 : min_segs = 7'b0010010;
            3 : min_segs = 7'b0000110;
            4 : min_segs = 7'b1001100;
            5 : min_segs = 7'b0100100;
            6 : min_segs = 7'b0100000;
            7 : min_segs = 7'b0001111;
            8 : min_segs = 7'b0000000;
            9 : min_segs = 7'b0000100;
            default : min_segs = 7'b1111111; 
        endcase
    end


    
endmodule

Nivel02/decoder_7seg_tb.v
`timescale 1ns/1ps
`include "decoder_7seg.v"

module decoder_7seg_tb ();

reg[0:3] sec_ones_tb; reg[0:3] sec_tens_tb; reg[0:3] min_tb;
wire [0:6] sec_ones_segs_tb; wire [0:6]  sec_tens_segs_tb; wire [0:6]  min_segs_tb;

decoder_7seg UUT(.sec_ones(sec_ones_tb), .sec_tens(sec_tens_tb), .min(min_tb), .sec_ones_segs(sec_ones_segs_tb),
.sec_tens_segs(sec_tens_segs_tb), .min_segs(min_segs_tb));

initial begin
    $dumpfile("decoder_7seg_tb.vcd");
    $dumpvars(0, decoder_7seg_tb);
    #10
    sec_ones_tb = 8; sec_tens_tb = 1; min_tb = 2;
    #2
    sec_ones_tb = 7; #2
    sec_ones_tb = 6; #2
    sec_ones_tb = 0;  sec_tens_tb = 0; #3
    sec_ones_tb = 9;  #2
    sec_ones_tb = 8;  #2
    sec_ones_tb = 1;  #2
    sec_ones_tb = 9;  sec_tens_tb = 5; min_tb = 1;#2
    $finish;


end
    
endmodule

Nivel02/decoder_7seg_tb.vcd
$date
	Fri Dec 17 21:27:32 2021
$end
$version
	Icarus Verilog
$end
$timescale
	1ps
$end
$scope module decoder_7seg_tb $end
$var wire 7 ! sec_tens_segs_tb [0:6] $end
$var wire 7 " sec_ones_segs_tb [0:6] $end
$var wire 7 # min_segs_tb [0:6] $end
$var reg 4 $ min_tb [0:3] $end
$var reg 4 % sec_ones_tb [0:3] $end
$var reg 4 & sec_tens_tb [0:3] $end
$scope module UUT $end
$var wire 4 ' min [3:0] $end
$var wire 4 ( sec_ones [3:0] $end
$var wire 4 ) sec_tens [3:0] $end
$var reg 7 * min_segs [0:6] $end
$var reg 7 + sec_ones_segs [0:6] $end
$var reg 7 , sec_tens_segs [0:6] $end
$upscope $end
$upscope $end
$enddefinitions $end
#0
$dumpvars
bx ,
bx +
bx *
bx )
bx (
bx '
bx &
bx %
bx $
bx #
bx "
bx !
$end
#10000
b10010 #
b10010 *
b1001111 !
b1001111 ,
b0 "
b0 +
b10 $
b10 '
b1 &
b1 )
b1000 %
b1000 (
#12000
b1111 "
b1111 +
b111 %
b111 (
#14000
b100000 "
b100000 +
b110 %
b110 (
#16000
b1 !
b1 ,
b1 "
b1 +
b0 &
b0 )
b0 %
b0 (
#19000
b100 "
b100 +
b1001 %
b1001 (
#21000
b0 "
b0 +
b1000 %
b1000 (
#23000
b1001111 "
b1001111 +
b1 %
b1 (
#25000
b1001111 #
b1001111 *
b100100 !
b100100 ,
b100 "
b100 +
b1 $
b1 '
b101 &
b101 )
b1001 %
b1001 (
