Nivel03/mux.v
module mux (
    input wire D0, D1,
    input wire Sel,
    output reg out
);

always @(*) begin
    out = (Sel == 0) ? D0 : D1;
end
    
endmodule

Nivel03/nonrecycle_counter.v
module nonrecycle_counter (
    input wire clr, clk,
    output reg out
);
reg[2:0] count;
    always @(posedge clk or clr) begin
        if(clr == 1) begin count <= 0; out <= 0; end
        else if (count == 7) count <= 7;
        else count <= count+1;
        if(count == 4) out <= 1;
    end
endmodule

Nivel03/clk_div.v
module clk_div 
#( 
parameter WIDTH = 6, 
parameter N = 50
)
(input wire clk, output wire clk_out);
 
reg [WIDTH-1:0] r_reg;
wire [WIDTH-1:0] r_nxt;
reg clk_track;

initial r_reg = 0;
initial clk_track = 1'b0;
 
always @(posedge clk)
 begin
    if (r_nxt == N)
 	   begin
	     r_reg <= 0;
	     clk_track <= ~clk_track;
	   end  
    else begin
      r_reg <= r_nxt;
    end
end
 
 assign r_nxt = r_reg+1;   	      
 assign clk_out = clk_track;
endmodule

Nivel03/PriorityEncoder.v

module PriorityEncoder(
  input wire [9:0] keypad,
  input wire enablen,
  output reg [3:0] D,
  output reg V
);
  
  always @ (*)
  begin
	if(enablen) begin
		D = 0; V = 1;
	end else begin
		D = (keypad[9]) ? (9) :
			 (keypad[8]) ? (8) :
			 (keypad[7]) ? (7) :
			 (keypad[6]) ? (6) :
			 (keypad[5]) ? (5) :
			 (keypad[4]) ? (4) :
			 (keypad[3]) ? (3) :
			 (keypad[2]) ? (2) :
			 (keypad[1]) ? (1) :
			 (keypad[0]) ? (0) : 4'bxxxx;
		V = (keypad[9]) ? 0 :
			 (keypad[8]) ? 0 :
			 (keypad[7]) ? 0 :
			 (keypad[6]) ? 0 :
			 (keypad[5]) ? 0 :
			 (keypad[4]) ? 0 :
			 (keypad[3]) ? 0 :
			 (keypad[2]) ? 0 :
			 (keypad[1]) ? 0 :
			 (keypad[0]) ? 0 : 1;
   end
  end
  
  
endmodule

Nivel02/encoder.v
`include "..\Nivel03\PriorityEncoder.v"
`include "..\Nivel03\nonrecycle_counter.v"
`include "..\Nivel03\clk_div.v"
`include "..\Nivel03\mux.v"

module encoder (
    input wire[9:0] keypad, input wire enablen, clk,
    output wire[3:0] D, output wire loadn, pgt_1Hz
);

wire clk_1hz;
wire delay;

PriorityEncoder codificador(keypad[9:0], enablen, D[3:0], loadn);
clk_div divisor_freq(clk, clk_1hz);
nonrecycle_counter contador(loadn, clk, delay);
mux multiplexador(delay, clk_1hz, enablen, pgt_1Hz);
    
endmodule

Nivel02/encoder_tb.v
`timescale 1ms/1ns
`include "encoder.v"

module encoder_tb ();

reg[9:0] keypad_tb; reg enablen_tb; reg clk_tb;
wire[3:0] D_tb; wire loadn_tb; wire pgt_1Hz_tb;

encoder UUT( .keypad(keypad_tb), .enablen(enablen_tb), .clk(clk_tb), .D(D_tb), 
 .loadn(loadn_tb), .pgt_1Hz(pgt_1Hz_tb));

always #10 clk_tb = ~clk_tb;

initial begin
    $dumpfile("encoder_tb.vcd");
    $dumpvars(0, encoder_tb);
    clk_tb = 0;
    keypad_tb = 9'b000000000;
    enablen_tb = 1;
    #20
    enablen_tb = 0;
    #10
    keypad_tb[5] = 1;
    #90
    keypad_tb[5] = 0;
    #50
    keypad_tb[1] = 1;
    #100
    keypad_tb[1] = 0;
    #100
    enablen_tb = 1;
    #1500


    $stop;
 
end
endmodule

Nivel02/encoder_tb.vcd
$date
	Wed Dec 15 15:28:36 2021
$end
$version
	Icarus Verilog
$end
$timescale
	1ns
$end
$scope module encoder_tb $end
$var wire 1 ! pgt_1Hz_tb $end
$var wire 1 " loadn_tb $end
$var wire 4 # D_tb [3:0] $end
$var reg 1 $ clk_tb $end
$var reg 1 % enablen_tb $end
$var reg 10 & keypad_tb [9:0] $end
$scope module UUT $end
$var wire 1 $ clk $end
$var wire 1 % enablen $end
$var wire 10 ' keypad [9:0] $end
$var wire 1 ! pgt_1Hz $end
$var wire 1 " loadn $end
$var wire 1 ( delay $end
$var wire 1 ) clk_1hz $end
$var wire 4 * D [3:0] $end
$scope module codificador $end
$var wire 1 % enablen $end
$var wire 10 + keypad [9:0] $end
$var reg 4 , D [3:0] $end
$var reg 1 " V $end
$upscope $end
$scope module contador $end
$var wire 1 $ clk $end
$var wire 1 " clr $end
$var reg 3 - count [2:0] $end
$var reg 1 ( out $end
$upscope $end
$scope module divisor_freq $end
$var wire 1 $ clk $end
$var wire 1 ) clk_out $end
$var wire 6 . r_nxt [5:0] $end
$var reg 1 / clk_track $end
$var reg 6 0 r_reg [5:0] $end
$upscope $end
$scope module multiplexador $end
$var wire 1 ( D0 $end
$var wire 1 ) D1 $end
$var wire 1 % Sel $end
$var reg 1 ! out $end
$upscope $end
$upscope $end
$upscope $end
$enddefinitions $end
#0
$dumpvars
b0 0
0/
b1 .
b0 -
b0 ,
b0 +
b0 *
0)
0(
b0 '
b0 &
1%
0$
b0 #
1"
0!
$end
#10000000
b10 .
b1 0
1$
#20000000
bx #
bx *
bx ,
0$
0%
#30000000
b1 -
b11 .
b10 0
0"
b101 #
b101 *
b101 ,
1$
b100000 &
b100000 '
b100000 +
#40000000
0$
#50000000
b10 -
b100 .
b11 0
1$
#60000000
0$
#70000000
b11 -
b101 .
b100 0
1$
#80000000
0$
#90000000
b100 -
b110 .
b101 0
1$
#100000000
0$
#110000000
1!
1(
b101 -
b111 .
b110 0
1$
#120000000
0!
0(
b0 -
1"
bx #
bx *
bx ,
0$
b0 &
b0 '
b0 +
#130000000
b1000 .
b111 0
1$
#140000000
0$
#150000000
b1001 .
b1000 0
1$
#160000000
0$
#170000000
b1 -
b1010 .
b1001 0
0"
b1 #
b1 *
b1 ,
1$
b10 &
b10 '
b10 +
#180000000
0$
#190000000
b10 -
b1011 .
b1010 0
1$
#200000000
0$
#210000000
b11 -
b1100 .
b1011 0
1$
#220000000
0$
#230000000
b100 -
b1101 .
b1100 0
1$
#240000000
0$
#250000000
1!
1(
b101 -
b1110 .
b1101 0
1$
#260000000
0$
#270000000
0!
0(
b0 -
b1111 .
b1110 0
1"
bx #
bx *
bx ,
1$
b0 &
b0 '
b0 +
#280000000
0$
#290000000
b10000 .
b1111 0
1$
#300000000
0$
#310000000
b10001 .
b10000 0
1$
#320000000
0$
#330000000
b10010 .
b10001 0
1$
#340000000
0$
#350000000
b10011 .
b10010 0
1$
#360000000
0$
#370000000
b10100 .
b10011 0
b0 #
b0 *
b0 ,
1$
1%
#380000000
0$
#390000000
b10101 .
b10100 0
1$
#400000000
0$
#410000000
b10110 .
b10101 0
1$
#420000000
0$
#430000000
b10111 .
b10110 0
1$
#440000000
0$
#450000000
b11000 .
b10111 0
1$
#460000000
0$
#470000000
b11001 .
b11000 0
1$
#480000000
0$
#490000000
b11010 .
b11001 0
1$
#500000000
0$
#510000000
b11011 .
b11010 0
1$
#520000000
0$
#530000000
b11100 .
b11011 0
1$
#540000000
0$
#550000000
b11101 .
b11100 0
1$
#560000000
0$
#570000000
b11110 .
b11101 0
1$
#580000000
0$
#590000000
b11111 .
b11110 0
1$
#600000000
0$
#610000000
b100000 .
b11111 0
1$
#620000000
0$
#630000000
b100001 .
b100000 0
1$
#640000000
0$
#650000000
b100010 .
b100001 0
1$
#660000000
0$
#670000000
b100011 .
b100010 0
1$
#680000000
0$
#690000000
b100100 .
b100011 0
1$
#700000000
0$
#710000000
b100101 .
b100100 0
1$
#720000000
0$
#730000000
b100110 .
b100101 0
1$
#740000000
0$
#750000000
b100111 .
b100110 0
1$
#760000000
0$
#770000000
b101000 .
b100111 0
1$
#780000000
0$
#790000000
b101001 .
b101000 0
1$
#800000000
0$
#810000000
b101010 .
b101001 0
1$
#820000000
0$
#830000000
b101011 .
b101010 0
1$
#840000000
0$
#850000000
b101100 .
b101011 0
1$
#860000000
0$
#870000000
b101101 .
b101100 0
1$
#880000000
0$
#890000000
b101110 .
b101101 0
1$
#900000000
0$
#910000000
b101111 .
b101110 0
1$
#920000000
0$
#930000000
b110000 .
b101111 0
1$
#940000000
0$
#950000000
b110001 .
b110000 0
1$
#960000000
0$
#970000000
b110010 .
b110001 0
1$
#980000000
0$
#990000000
1!
1)
1/
b1 .
b0 0
1$
#1000000000
0$
#1010000000
b10 .
b1 0
1$
#1020000000
0$
#1030000000
b11 .
b10 0
1$
#1040000000
0$
#1050000000
b100 .
b11 0
1$
#1060000000
0$
#1070000000
b101 .
b100 0
1$
#1080000000
0$
#1090000000
b110 .
b101 0
1$
#1100000000
0$
#1110000000
b111 .
b110 0
1$
#1120000000
0$
#1130000000
b1000 .
b111 0
1$
#1140000000
0$
#1150000000
b1001 .
b1000 0
1$
#1160000000
0$
#1170000000
b1010 .
b1001 0
1$
#1180000000
0$
#1190000000
b1011 .
b1010 0
1$
#1200000000
0$
#1210000000
b1100 .
b1011 0
1$
#1220000000
0$
#1230000000
b1101 .
b1100 0
1$
#1240000000
0$
#1250000000
b1110 .
b1101 0
1$
#1260000000
0$
#1270000000
b1111 .
b1110 0
1$
#1280000000
0$
#1290000000
b10000 .
b1111 0
1$
#1300000000
0$
#1310000000
b10001 .
b10000 0
1$
#1320000000
0$
#1330000000
b10010 .
b10001 0
1$
#1340000000
0$
#1350000000
b10011 .
b10010 0
1$
#1360000000
0$
#1370000000
b10100 .
b10011 0
1$
#1380000000
0$
#1390000000
b10101 .
b10100 0
1$
#1400000000
0$
#1410000000
b10110 .
b10101 0
1$
#1420000000
0$
#1430000000
b10111 .
b10110 0
1$
#1440000000
0$
#1450000000
b11000 .
b10111 0
1$
#1460000000
0$
#1470000000
b11001 .
b11000 0
1$
#1480000000
0$
#1490000000
b11010 .
b11001 0
1$
#1500000000
0$
#1510000000
b11011 .
b11010 0
1$
#1520000000
0$
#1530000000
b11100 .
b11011 0
1$
#1540000000
0$
#1550000000
b11101 .
b11100 0
1$
#1560000000
0$
#1570000000
b11110 .
b11101 0
1$
#1580000000
0$
#1590000000
b11111 .
b11110 0
1$
#1600000000
0$
#1610000000
b100000 .
b11111 0
1$
#1620000000
0$
#1630000000
b100001 .
b100000 0
1$
#1640000000
0$
#1650000000
b100010 .
b100001 0
1$
#1660000000
0$
#1670000000
b100011 .
b100010 0
1$
#1680000000
0$
#1690000000
b100100 .
b100011 0
1$
#1700000000
0$
#1710000000
b100101 .
b100100 0
1$
#1720000000
0$
#1730000000
b100110 .
b100101 0
1$
#1740000000
0$
#1750000000
b100111 .
b100110 0
1$
#1760000000
0$
#1770000000
b101000 .
b100111 0
1$
#1780000000
0$
#1790000000
b101001 .
b101000 0
1$
#1800000000
0$
#1810000000
b101010 .
b101001 0
1$
#1820000000
0$
#1830000000
b101011 .
b101010 0
1$
#1840000000
0$
#1850000000
b101100 .
b101011 0
1$
