Nivel03/counterMod10.v
module counterMod10 (
    input wire [3:0] CNT_in,
    input wire loadn, clrn, clk, en,
    output reg [3:0] CNT, 
    output reg tc, zero
);

always @(posedge clk) begin
        if(clrn == 0) CNT <= 0;
        else if(loadn == 0) CNT <= CNT_in; 
        else if (CNT == 0 && en == 1) CNT <= 9;
        else if (CNT > 9) CNT <= 9; 
        else if(en == 1) CNT <= CNT - 1;
        else CNT <= CNT;
end

always @(CNT or en) begin
    if((en == 1) && (CNT == 4'b0000)) begin
        tc <= 1; 
        zero <= 1;
    end
    else begin
        tc <= 0;
        zero <= 0;
    end
end

endmodule

Nivel03/counterMod6.v
module counterMod6 (
    input wire [3:0] CNT_in,
    input wire loadn, clrn, clk, en,
    output reg [3:0] CNT, 
    output reg tc, zero
);

always @(posedge clk) begin
        if(clrn == 0) CNT <= 0;
        else if(loadn == 0) CNT <= CNT_in; 
        else if (CNT == 0 && en == 1) CNT <= 5;
        else if (CNT > 5) CNT <= 5;
        else if(en == 1) CNT <= CNT - 1;
        else CNT <= CNT;

end
always @(CNT or en) begin
    if((en == 1) && (CNT == 4'b0000)) begin
        tc <= 1; 
        zero <= 1;
    end
    else begin
        tc <= 0;
        zero <= 0;
    end
end

endmodule

Nivel02/timer.v
`include "..\Nivel03\counterMod10.v"
`include "..\Nivel03\counterMod6.v"

module timer (
    input wire [3:0] CNT_in,
    input wire loadn, clrn, clk, en,
    output wire [3:0] sec_ones, output wire [3:0] sec_tens, output wire [3:0] mins,
    output wire zero
);

wire tc1, tc2, tc3, zero1, zero2, zero3;

counterMod10 segundos(CNT_in[3:0], loadn, clrn, clk, en, sec_ones[3:0], tc1, zero1);
counterMod6 segundos_decimais(sec_ones[3:0], loadn, clrn, clk, tc1, sec_tens[3:0], tc2, zero2);
counterMod10 minutos(sec_tens[3:0], loadn, clrn, clk, tc2, mins[3:0], tc3, zero3);

assign zero = zero1 && zero2 && zero3;

endmodule

Nivel02/timer_tb.v
`timescale 1ns/1ps
`include "timer.v"

module timer_tb ();

reg [0:3] CNT_in_tb;
reg loadn_tb; reg clrn_tb; reg clk_tb; reg en_tb;
wire [0:3] sec_ones_tb;
wire [0:3] sec_tens_tb;
wire [0:3] mins_tb;
wire zero_tb;

timer UUT(.CNT_in(CNT_in_tb), .loadn(loadn_tb), .clrn(clrn_tb), .clk(clk_tb), .en(en_tb), .sec_ones(sec_ones_tb), .sec_tens(sec_tens_tb), .mins(mins_tb), .zero(zero_tb));

always #5 clk_tb = ~clk_tb;

initial begin
    $dumpfile("timer_tb.vcd");
    $dumpvars(0, timer_tb);
    
    clrn_tb = 1; en_tb = 0;
    clk_tb = 0;
    loadn_tb = 0;

    CNT_in_tb = 1;
    #6
    CNT_in_tb = 2;
    #10
    CNT_in_tb = 3;
    #10
    loadn_tb = 1;
    #5
    en_tb = 1;
    #1000

    en_tb = 0; loadn_tb = 0;

    CNT_in_tb = 1;
    #6
    CNT_in_tb = 2;
    #10
    CNT_in_tb = 3;
    #10
    CNT_in_tb = 5;
    #10
    loadn_tb = 1;
    #5
    en_tb = 1;
    #1000
    clrn_tb = 0;
    #10

    $stop;
 
end
endmodule

Nivel02/timer_tb.vcd
$date
	Wed Dec 15 15:47:57 2021
$end
$version
	Icarus Verilog
$end
$timescale
	1ps
$end
$scope module timer_tb $end
$var wire 1 ! zero_tb $end
$var wire 4 " sec_tens_tb [0:3] $end
$var wire 4 # sec_ones_tb [0:3] $end
$var wire 4 $ mins_tb [0:3] $end
$var reg 4 % CNT_in_tb [0:3] $end
$var reg 1 & clk_tb $end
$var reg 1 ' clrn_tb $end
$var reg 1 ( en_tb $end
$var reg 1 ) loadn_tb $end
$scope module UUT $end
$var wire 4 * CNT_in [3:0] $end
$var wire 1 & clk $end
$var wire 1 ' clrn $end
$var wire 1 ( en $end
$var wire 1 ) loadn $end
$var wire 1 ! zero $end
$var wire 1 + zero3 $end
$var wire 1 , zero2 $end
$var wire 1 - zero1 $end
$var wire 1 . tc3 $end
$var wire 1 / tc2 $end
$var wire 1 0 tc1 $end
$var wire 4 1 sec_tens [3:0] $end
$var wire 4 2 sec_ones [3:0] $end
$var wire 4 3 mins [3:0] $end
$scope module minutos $end
$var wire 1 & clk $end
$var wire 1 ' clrn $end
$var wire 1 ) loadn $end
$var wire 1 / en $end
$var wire 4 4 CNT_in [3:0] $end
$var reg 4 5 CNT [3:0] $end
$var reg 1 . tc $end
$var reg 1 + zero $end
$upscope $end
$scope module segundos $end
$var wire 4 6 CNT_in [3:0] $end
$var wire 1 & clk $end
$var wire 1 ' clrn $end
$var wire 1 ( en $end
$var wire 1 ) loadn $end
$var reg 4 7 CNT [3:0] $end
$var reg 1 0 tc $end
$var reg 1 - zero $end
$upscope $end
$scope module segundos_decimais $end
$var wire 4 8 CNT_in [3:0] $end
$var wire 1 & clk $end
$var wire 1 ' clrn $end
$var wire 1 0 en $end
$var wire 1 ) loadn $end
$var reg 4 9 CNT [3:0] $end
$var reg 1 / tc $end
$var reg 1 , zero $end
$upscope $end
$upscope $end
$upscope $end
$enddefinitions $end
#0
$dumpvars
bx 9
bx 8
bx 7
b1 6
bx 5
bx 4
bx 3
bx 2
bx 1
00
0/
0.
0-
0,
0+
b1 *
0)
0(
1'
0&
b1 %
bx $
bx #
bx "
0!
$end
#5000
b1 #
b1 2
b1 7
b1 8
1&
#6000
b10 %
b10 *
b10 6
#10000
0&
#15000
b1 "
b1 1
b1 4
b1 9
b10 #
b10 2
b10 7
b10 8
1&
#16000
b11 %
b11 *
b11 6
#20000
0&
#25000
b11 #
b11 2
b11 7
b11 8
b10 "
b10 1
b10 4
b10 9
b1 $
b1 3
b1 5
1&
#26000
1)
#30000
0&
#31000
1(
#35000
b10 #
b10 2
b10 7
b10 8
1&
#40000
0&
#45000
b1 #
b1 2
b1 7
b1 8
1&
#50000
0&
#55000
1-
10
b0 #
b0 2
b0 7
b0 8
1&
#60000
0&
#65000
0-
00
b1001 #
b1001 2
b1001 7
b1001 8
b1 "
b1 1
b1 4
b1 9
1&
#70000
0&
#75000
b1000 #
b1000 2
b1000 7
b1000 8
1&
#80000
0&
#85000
b111 #
b111 2
b111 7
b111 8
1&
#90000
0&
#95000
b110 #
b110 2
b110 7
b110 8
1&
#100000
0&
#105000
b101 #
b101 2
b101 7
b101 8
1&
#110000
0&
#115000
b100 #
b100 2
b100 7
b100 8
1&
#120000
0&
#125000
b11 #
b11 2
b11 7
b11 8
1&
#130000
0&
#135000
b10 #
b10 2
b10 7
b10 8
1&
#140000
0&
#145000
b1 #
b1 2
b1 7
b1 8
1&
#150000
0&
#155000
1-
10
b0 #
b0 2
b0 7
b0 8
1&
#160000
0&
#165000
0-
00
0,
0/
b1001 #
b1001 2
b1001 7
b1001 8
b0 "
b0 1
b0 4
b0 9
1&
#170000
0&
#175000
b1000 #
b1000 2
b1000 7
b1000 8
1&
#180000
0&
#185000
b111 #
b111 2
b111 7
b111 8
1&
#190000
0&
#195000
b110 #
b110 2
b110 7
b110 8
1&
#200000
0&
#205000
b101 #
b101 2
b101 7
b101 8
1&
#210000
0&
#215000
b100 #
b100 2
b100 7
b100 8
1&
#220000
0&
#225000
b11 #
b11 2
b11 7
b11 8
1&
#230000
0&
#235000
b10 #
b10 2
b10 7
b10 8
1&
#240000
0&
#245000
b1 #
b1 2
b1 7
b1 8
1&
#250000
0&
#255000
1,
1/
1-
10
b0 #
b0 2
b0 7
b0 8
1&
#260000
0&
#265000
0!
0-
00
0,
0/
0+
0.
b1001 #
b1001 2
b1001 7
b1001 8
b101 "
b101 1
b101 4
b101 9
b0 $
b0 3
b0 5
1&
#270000
0&
#275000
b1000 #
b1000 2
b1000 7
b1000 8
1&
#280000
0&
#285000
b111 #
b111 2
b111 7
b111 8
1&
#290000
0&
#295000
b110 #
b110 2
b110 7
b110 8
1&
#300000
0&
#305000
b101 #
b101 2
b101 7
b101 8
1&
#310000
0&
#315000
b100 #
b100 2
b100 7
b100 8
1&
#320000
0&
#325000
b11 #
b11 2
b11 7
b11 8
1&
#330000
0&
#335000
b10 #
b10 2
b10 7
b10 8
1&
#340000
0&
#345000
b1 #
b1 2
b1 7
b1 8
1&
#350000
0&
#355000
1-
10
b0 #
b0 2
b0 7
b0 8
1&
#360000
0&
#365000
0-
00
b1001 #
b1001 2
b1001 7
b1001 8
b100 "
b100 1
b100 4
b100 9
1&
#370000
0&
#375000
b1000 #
b1000 2
b1000 7
b1000 8
1&
#380000
0&
#385000
b111 #
b111 2
b111 7
b111 8
1&
#390000
0&
#395000
b110 #
b110 2
b110 7
b110 8
1&
#400000
0&
#405000
b101 #
b101 2
b101 7
b101 8
1&
#410000
0&
#415000
b100 #
b100 2
b100 7
b100 8
1&
#420000
0&
#425000
b11 #
b11 2
b11 7
b11 8
1&
#430000
0&
#435000
b10 #
b10 2
b10 7
b10 8
1&
#440000
0&
#445000
b1 #
b1 2
b1 7
b1 8
1&
#450000
0&
#455000
1-
10
b0 #
b0 2
b0 7
b0 8
1&
#460000
0&
#465000
0-
00
b1001 #
b1001 2
b1001 7
b1001 8
b11 "
b11 1
b11 4
b11 9
1&
#470000
0&
#475000
b1000 #
b1000 2
b1000 7
b1000 8
1&
#480000
0&
#485000
b111 #
b111 2
b111 7
b111 8
1&
#490000
0&
#495000
b110 #
b110 2
b110 7
b110 8
1&
#500000
0&
#505000
b101 #
b101 2
b101 7
b101 8
1&
#510000
0&
#515000
b100 #
b100 2
b100 7
b100 8
1&
#520000
0&
#525000
b11 #
b11 2
b11 7
b11 8
1&
#530000
0&
#535000
b10 #
b10 2
b10 7
b10 8
1&
#540000
0&
#545000
b1 #
b1 2
b1 7
b1 8
1&
#550000
0&
#555000
1-
10
b0 #
b0 2
b0 7
b0 8
1&
#560000
0&
#565000
0-
00
b1001 #
b1001 2
b1001 7
b1001 8
b10 "
b10 1
b10 4
b10 9
1&
#570000
0&
#575000
b1000 #
b1000 2
b1000 7
b1000 8
1&
#580000
0&
#585000
b111 #
b111 2
b111 7
b111 8
1&
#590000
0&
#595000
b110 #
b110 2
b110 7
b110 8
1&
#600000
0&
#605000
b101 #
b101 2
b101 7
b101 8
1&
#610000
0&
#615000
b100 #
b100 2
b100 7
b100 8
1&
#620000
0&
#625000
b11 #
b11 2
b11 7
b11 8
1&
#630000
0&
#635000
b10 #
b10 2
b10 7
b10 8
1&
#640000
0&
#645000
b1 #
b1 2
b1 7
b1 8
1&
#650000
0&
#655000
1-
10
b0 #
b0 2
b0 7
b0 8
1&
#660000
0&
#665000
0-
00
b1001 #
b1001 2
b1001 7
b1001 8
b1 "
b1 1
b1 4
b1 9
1&
#670000
0&
#675000
b1000 #
b1000 2
b1000 7
b1000 8
1&
#680000
0&
#685000
b111 #
b111 2
b111 7
b111 8
1&
#690000
0&
#695000
b110 #
b110 2
b110 7
b110 8
1&
#700000
0&
#705000
b101 #
b101 2
b101 7
b101 8
1&
#710000
0&
#715000
b100 #
b100 2
b100 7
b100 8
1&
#720000
0&
#725000
b11 #
b11 2
b11 7
b11 8
1&
#730000
0&
#735000
b10 #
b10 2
b10 7
b10 8
1&
#740000
0&
#745000
b1 #
b1 2
b1 7
b1 8
1&
#750000
0&
#755000
1-
10
b0 #
b0 2
b0 7
b0 8
1&
#760000
0&
#765000
0+
0.
0-
00
0,
0/
b1001 #
b1001 2
b1001 7
b1001 8
b0 "
b0 1
b0 4
b0 9
1&
#770000
0&
#775000
b1000 #
b1000 2
b1000 7
b1000 8
1&
#780000
0&
#785000
b111 #
b111 2
b111 7
b111 8
1&
#790000
0&
#795000
b110 #
b110 2
b110 7
b110 8
1&
#800000
0&
#805000
b101 #
b101 2
b101 7
b101 8
1&
#810000
0&
#815000
b100 #
b100 2
b100 7
b100 8
1&
#820000
0&
#825000
b11 #
b11 2
b11 7
b11 8
1&
#830000
0&
#835000
b10 #
b10 2
b10 7
b10 8
1&
#840000
0&
#845000
b1 #
b1 2
b1 7
b1 8
1&
#850000
0&
#855000
1!
1+
1.
1,
1/
1-
10
b0 #
b0 2
b0 7
b0 8
1&
#860000
0&
#865000
0!
0-
00
0,
0/
0+
0.
b1001 #
b1001 2
b1001 7
b1001 8
b101 "
b101 1
b101 4
b101 9
b1001 $
b1001 3
b1001 5
1&
#870000
0&
#875000
b1000 #
b1000 2
b1000 7
b1000 8
1&
#880000
0&
#885000
b111 #
b111 2
b111 7
b111 8
1&
#890000
0&
#895000
b110 #
b110 2
b110 7
b110 8
1&
#900000
0&
#905000
b101 #
b101 2
b101 7
b101 8
1&
#910000
0&
#915000
b100 #
b100 2
b100 7
b100 8
1&
#920000
0&
#925000
b11 #
b11 2
b11 7
b11 8
1&
#930000
0&
#935000
b10 #
b10 2
b10 7
b10 8
1&
#940000
0&
#945000
b1 #
b1 2
b1 7
b1 8
1&
#950000
0&
#955000
1-
10
b0 #
b0 2
b0 7
b0 8
1&
#960000
0&
#965000
0-
00
b1001 #
b1001 2
b1001 7
b1001 8
b100 "
b100 1
b100 4
b100 9
1&
#970000
0&
#975000
b1000 #
b1000 2
b1000 7
b1000 8
1&
#980000
0&
#985000
b111 #
b111 2
b111 7
b111 8
1&
#990000
0&
#995000
b110 #
b110 2
b110 7
b110 8
1&
#1000000
0&
#1005000
b101 #
b101 2
b101 7
b101 8
1&
#1010000
0&
#1015000
b100 #
b100 2
b100 7
b100 8
1&
#1020000
0&
#1025000
b11 #
b11 2
b11 7
b11 8
1&
#1030000
0&
#1031000
b1 %
b1 *
b1 6
0)
0(
#1035000
b100 $
b100 3
b100 5
b11 "
b11 1
b11 4
b11 9
b1 #
b1 2
b1 7
b1 8
1&
#1037000
b10 %
b10 *
b10 6
#1040000
0&
#1045000
b10 #
b10 2
b10 7
b10 8
b1 "
b1 1
b1 4
b1 9
b11 $
b11 3
b11 5
1&
#1047000
b11 %
b11 *
b11 6
#1050000
0&
#1055000
b1 $
b1 3
b1 5
b10 "
b10 1
b10 4
b10 9
b11 #
b11 2
b11 7
b11 8
1&
#1057000
b101 %
b101 *
b101 6
#1060000
0&
#1065000
b101 #
b101 2
b101 7
b101 8
b11 "
b11 1
b11 4
b11 9
b10 $
b10 3
b10 5
1&
#1067000
1)
#1070000
0&
#1072000
1(
#1075000
b100 #
b100 2
b100 7
b100 8
1&
#1080000
0&
#1085000
b11 #
b11 2
b11 7
b11 8
1&
#1090000
0&
#1095000
b10 #
b10 2
b10 7
b10 8
1&
#1100000
0&
#1105000
b1 #
b1 2
b1 7
b1 8
1&
#1110000
0&
#1115000
1-
10
b0 #
b0 2
b0 7
b0 8
1&
#1120000
0&
#1125000
0-
00
b1001 #
b1001 2
b1001 7
b1001 8
b10 "
b10 1
b10 4
b10 9
1&
#1130000
0&
#1135000
b1000 #
b1000 2
b1000 7
b1000 8
1&
#1140000
0&
#1145000
b111 #
b111 2
b111 7
b111 8
1&
#1150000
0&
#1155000
b110 #
b110 2
b110 7
b110 8
1&
#1160000
0&
#1165000
b101 #
b101 2
b101 7
b101 8
1&
#1170000
0&
#1175000
b100 #
b100 2
b100 7
b100 8
1&
#1180000
0&
#1185000
b11 #
b11 2
b11 7
b11 8
1&
#1190000
0&
#1195000
b10 #
b10 2
b10 7
b10 8
1&
#1200000
0&
#1205000
b1 #
b1 2
b1 7
b1 8
1&
#1210000
0&
#1215000
1-
10
b0 #
b0 2
b0 7
b0 8
1&
#1220000
0&
#1225000
0-
00
b1001 #
b1001 2
b1001 7
b1001 8
b1 "
b1 1
b1 4
b1 9
1&
#1230000
0&
#1235000
b1000 #
b1000 2
b1000 7
b1000 8
1&
#1240000
0&
#1245000
b111 #
b111 2
b111 7
b111 8
1&
#1250000
0&
#1255000
b110 #
b110 2
b110 7
b110 8
1&
#1260000
0&
#1265000
b101 #
b101 2
b101 7
b101 8
1&
#1270000
0&
#1275000
b100 #
b100 2
b100 7
b100 8
1&
#1280000
0&
#1285000
b11 #
b11 2
b11 7
b11 8
1&
#1290000
0&
#1295000
b10 #
b10 2
b10 7
b10 8
1&
#1300000
0&
#1305000
b1 #
b1 2
b1 7
b1 8
1&
#1310000
0&
#1315000
1-
10
b0 #
b0 2
b0 7
b0 8
1&
#1320000
0&
#1325000
0-
00
0,
0/
b1001 #
b1001 2
b1001 7
b1001 8
b0 "
b0 1
b0 4
b0 9
1&
#1330000
0&
#1335000
b1000 #
b1000 2
b1000 7
b1000 8
1&
#1340000
0&
#1345000
b111 #
b111 2
b111 7
b111 8
1&
#1350000
0&
#1355000
b110 #
b110 2
b110 7
b110 8
1&
#1360000
0&
#1365000
b101 #
b101 2
b101 7
b101 8
1&
#1370000
0&
#1375000
b100 #
b100 2
b100 7
b100 8
1&
#1380000
0&
#1385000
b11 #
b11 2
b11 7
b11 8
1&
#1390000
0&
#1395000
b10 #
b10 2
b10 7
b10 8
1&
#1400000
0&
#1405000
b1 #
b1 2
b1 7
b1 8
1&
#1410000
0&
#1415000
1,
1/
1-
10
b0 #
b0 2
b0 7
b0 8
1&
#1420000
0&
#1425000
0-
00
0,
0/
b1001 #
b1001 2
b1001 7
b1001 8
b101 "
b101 1
b101 4
b101 9
b1 $
b1 3
b1 5
1&
#1430000
0&
#1435000
b1000 #
b1000 2
b1000 7
b1000 8
1&
#1440000
0&
#1445000
b111 #
b111 2
b111 7
b111 8
1&
#1450000
0&
#1455000
b110 #
b110 2
b110 7
b110 8
1&
#1460000
0&
#1465000
b101 #
b101 2
b101 7
b101 8
1&
#1470000
0&
#1475000
b100 #
b100 2
b100 7
b100 8
1&
#1480000
0&
#1485000
b11 #
b11 2
b11 7
b11 8
1&
#1490000
0&
#1495000
b10 #
b10 2
b10 7
b10 8
1&
#1500000
0&
#1505000
b1 #
b1 2
b1 7
b1 8
1&
#1510000
0&
#1515000
1-
10
b0 #
b0 2
b0 7
b0 8
1&
#1520000
0&
#1525000
0-
00
b1001 #
b1001 2
b1001 7
b1001 8
b100 "
b100 1
b100 4
b100 9
1&
#1530000
0&
#1535000
b1000 #
b1000 2
b1000 7
b1000 8
1&
#1540000
0&
#1545000
b111 #
b111 2
b111 7
b111 8
1&
#1550000
0&
#1555000
b110 #
b110 2
b110 7
b110 8
1&
#1560000
0&
#1565000
b101 #
b101 2
b101 7
b101 8
1&
#1570000
0&
#1575000
b100 #
b100 2
b100 7
b100 8
1&
#1580000
0&
#1585000
b11 #
b11 2
b11 7
b11 8
1&
#1590000
0&
#1595000
b10 #
b10 2
b10 7
b10 8
1&
#1600000
0&
#1605000
b1 #
b1 2
b1 7
b1 8
1&
#1610000
0&
#1615000
1-
10
b0 #
b0 2
b0 7
b0 8
1&
#1620000
0&
#1625000
0-
00
b1001 #
b1001 2
b1001 7
b1001 8
b11 "
b11 1
b11 4
b11 9
1&
#1630000
0&
#1635000
b1000 #
b1000 2
b1000 7
b1000 8
1&
#1640000
0&
#1645000
b111 #
b111 2
b111 7
b111 8
1&
#1650000
0&
#1655000
b110 #
b110 2
b110 7
b110 8
1&
#1660000
0&
#1665000
b101 #
b101 2
b101 7
b101 8
1&
#1670000
0&
#1675000
b100 #
b100 2
b100 7
b100 8
1&
#1680000
0&
#1685000
b11 #
b11 2
b11 7
b11 8
1&
#1690000
0&
#1695000
b10 #
b10 2
b10 7
b10 8
1&
#1700000
0&
#1705000
b1 #
b1 2
b1 7
b1 8
1&
#1710000
0&
#1715000
1-
10
b0 #
b0 2
b0 7
b0 8
1&
#1720000
0&
#1725000
0-
00
b1001 #
b1001 2
b1001 7
b1001 8
b10 "
b10 1
b10 4
b10 9
1&
#1730000
0&
#1735000
b1000 #
b1000 2
b1000 7
b1000 8
1&
#1740000
0&
#1745000
b111 #
b111 2
b111 7
b111 8
1&
#1750000
0&
#1755000
b110 #
b110 2
b110 7
b110 8
1&
#1760000
0&
#1765000
b101 #
b101 2
b101 7
b101 8
1&
#1770000
0&
#1775000
b100 #
b100 2
b100 7
b100 8
1&
#1780000
0&
#1785000
b11 #
b11 2
b11 7
b11 8
1&
#1790000
0&
#1795000
b10 #
b10 2
b10 7
b10 8
1&
#1800000
0&
#1805000
b1 #
b1 2
b1 7
b1 8
1&
#1810000
0&
#1815000
1-
10
b0 #
b0 2
b0 7
b0 8
1&
#1820000
0&
#1825000
0-
00
b1001 #
b1001 2
b1001 7
b1001 8
b1 "
b1 1
b1 4
b1 9
1&
#1830000
0&
#1835000
b1000 #
b1000 2
b1000 7
b1000 8
1&
#1840000
0&
#1845000
b111 #
b111 2
b111 7
b111 8
1&
#1850000
0&
#1855000
b110 #
b110 2
b110 7
b110 8
1&
#1860000
0&
#1865000
b101 #
b101 2
b101 7
b101 8
1&
#1870000
0&
#1875000
b100 #
b100 2
b100 7
b100 8
1&
#1880000
0&
#1885000
b11 #
b11 2
b11 7
b11 8
1&
#1890000
0&
#1895000
b10 #
b10 2
b10 7
b10 8
1&
#1900000
0&
#1905000
b1 #
b1 2
b1 7
b1 8
1&
#1910000
0&
#1915000
1-
10
b0 #
b0 2
b0 7
b0 8
1&
#1920000
0&
#1925000
0-
00
0,
0/
b1001 #
b1001 2
b1001 7
b1001 8
b0 "
b0 1
b0 4
b0 9
1&
#1930000
0&
#1935000
b1000 #
b1000 2
b1000 7
b1000 8
1&
#1940000
0&
#1945000
b111 #
b111 2
b111 7
b111 8
1&
#1950000
0&
#1955000
b110 #
b110 2
b110 7
b110 8
1&
#1960000
0&
#1965000
b101 #
b101 2
b101 7
b101 8
1&
#1970000
0&
#1975000
b100 #
b100 2
b100 7
b100 8
1&
#1980000
0&
#1985000
b11 #
b11 2
b11 7
b11 8
1&
#1990000
0&
#1995000
b10 #
b10 2
b10 7
b10 8
1&
#2000000
0&
#2005000
b1 #
b1 2
b1 7
b1 8
1&
#2010000
0&
#2015000
1,
1/
1-
10
b0 #
b0 2
b0 7
b0 8
1&
#2020000
0&
#2025000
0!
0-
00
0,
0/
0+
0.
b1001 #
b1001 2
b1001 7
b1001 8
b101 "
b101 1
b101 4
b101 9
b0 $
b0 3
b0 5
1&
#2030000
0&
#2035000
b1000 #
b1000 2
b1000 7
b1000 8
1&
#2040000
0&
#2045000
b111 #
b111 2
b111 7
b111 8
1&
#2050000
0&
#2055000
b110 #
b110 2
b110 7
b110 8
1&
#2060000
0&
#2065000
b101 #
b101 2
b101 7
b101 8
1&
#2070000
0&
#2072000
0'
#2075000
1!
1+
1.
1,
1/
1-
10
b0 "
b0 1
b0 4
b0 9
b0 #
b0 2
b0 7
b0 8
1&
